README.md
setup.py
recoil/__init__.py
recoil.egg-info/PKG-INFO
recoil.egg-info/SOURCES.txt
recoil.egg-info/dependency_links.txt
recoil.egg-info/requires.txt
recoil.egg-info/top_level.txt