Metadata-Version: 2.1
Name: recoil
Version: 0.1.0
Summary: Simple Spring-inspired IoC framework for Python.
Home-page: https://gitlab.com/flitt3r/recoil
Author: flitt3r
License: MIT
Keywords: python ioc spring inversion of control
Platform: UNKNOWN
Classifier: Development Status :: 2 - Pre-Alpha
Classifier: Intended Audience :: Developers
Classifier: Topic :: Software Development
Classifier: Topic :: Software Development :: Libraries :: Python Modules
Classifier: Topic :: Utilities
Classifier: License :: OSI Approved :: MIT License
Classifier: Programming Language :: Python :: 3.6
Classifier: Programming Language :: Python :: 3.7
Provides-Extra: test
